{
  "transferencias": [
    {
      "id": "1",
      "valor": 35,
      "destino": "1212-1",
      "data": "2020-11-04T16:30:10.710Z"
    },
    {
      "id": "2",
      "valor": 40,
      "destino": "1213-1",
      "data": "2020-11-04T21:24:10.710Z"
    },
    {
      "id": "3",
      "valor": 12.5,
      "destino": "1214-1",
      "data": "2020-11-05T21:14:10.710Z"
    },
    {
      "valor": 200,
      "destino": "12555-5",
      "data": "2021-11-23T14:53:59.316Z",
      "id": "0yOedhf"
    },
    {
      "valor": 200,
      "destino": "5757-8",
      "data": "2021-11-23T14:54:13.652Z",
      "id": "AEtrZcj"
    },
    {
      "valor": 300,
      "destino": "52252-9",
      "data": "2021-11-23T15:19:48.869Z",
      "id": "KxIMoP7"
    },
    {
      "valor": 30,
      "destino": "5858-9",
      "data": "2021-11-23T15:32:16.109Z",
      "id": "yeFOJ2u"
    },
    {
      "valor": 120,
      "destino": "2325-9",
      "data": "2021-11-23T15:35:53.965Z",
      "id": "KYykrKT"
    },
    {
      "valor": 300,
      "destino": "5491-4",
      "data": "2021-11-23T15:55:59.308Z",
      "id": "pbh5jxF"
    },
    {
      "valor": 200,
      "destino": "5858-33",
      "data": "2021-11-23T15:57:19.391Z",
      "id": "hjRsqxO"
    },
    {
      "valor": 200,
      "destino": "1259-9",
      "data": "2021-11-23T15:58:38.678Z",
      "id": "jsDishk"
    },
    {
      "valor": 300,
      "destino": "1254-5",
      "data": "2021-11-23T16:03:59.224Z",
      "id": "iYZnW6v"
    },
    {
      "valor": 500,
      "destino": "5658-9",
      "data": "2021-11-23T16:11:09.377Z",
      "id": "_lxxTD_"
    }
  ]
}